{
  "timestamp": "2026-03-30T08:00:10.575403+00:00",
  "entry_id": 4,
  "analyst_summary": null,
  "strategist_proposal": null,
  "intent": {
    "action": "BUY",
    "pair": "BTC/USD",
    "price": 58103.0,
    "volume": 0.01704281,
    "reason": "RSI oversold. RSI=20.75 < 28. Mean reversion entry.",
    "rsi": 20.75
  },
  "risk_check": {
    "drawdown_pct": 0.98,
    "consecutive_losses": 2,
    "risk_level": "LOW"
  },
  "decision": "EXECUTE",
  "result": {
    "price": 58103.0,
    "volume": 0.01704281,
    "fee": 2.576422046386762
  },
  "refusal_proof": null,
  "refusal_impact": null,
  "prev_hash": "9126953f80951cda3a65ab730774e009f3f382e12e12a93499ab0d493c617a91",
  "entry_hash": "6519f0628529bc92cc6d388824ceec980ba3575a5096f2a8b7655a3c170e1c3d"
}