{
  "timestamp": "2026-03-30T07:06:41.792648+00:00",
  "entry_id": 4,
  "intent": {
    "action": "BUY",
    "pair": "BTC/USD",
    "price": 58103.0,
    "volume": 0.01704281,
    "reason": "RSI oversold. RSI=20.75 < 28. Mean reversion entry.",
    "rsi": 20.75
  },
  "risk_check": {
    "drawdown_pct": 0.98,
    "consecutive_losses": 2,
    "risk_level": "LOW"
  },
  "decision": "EXECUTE",
  "result": {
    "price": 58103.0,
    "volume": 0.01704281,
    "fee": 2.576422046386762
  },
  "refusal_proof": null,
  "refusal_impact": null,
  "prev_hash": "0f6d76214a58317aefecc649296e3488f94f499d24fffcc0860a6f3bc7ec4348",
  "entry_hash": "2b5612f1cbdbf03854c7d7c3a3f3b194649412fa1dccc8950e3805e00bff005a"
}